{
  "project_info": {
    "project_number": "399399775926",
    "project_id": "maxladarkmusic",
    "storage_bucket": "maxladarkmusic.appspot.com"
  },
  "client": [
    {
      "client_info": {
        "mobilesdk_app_id": "1:399399775926:android:ff2982305e728398f94017",
        "android_client_info": {
          "package_name": "com.maxlab.darkmusic"
        }
      },
      "oauth_client": [
        {
          "client_id": "399399775926-lus24v71ktdiaoh4s7pgujcm5n9dihen.apps.googleusercontent.com",
          "client_type": 3
        }
      ],
      "api_key": [
        {
          "current_key": "AIzaSyDbqE99SRAgPG_sw4jlxukQCVlSmvHO4c8"
        }
      ],
      "services": {
        "appinvite_service": {
          "other_platform_oauth_client": [
            {
              "client_id": "399399775926-lus24v71ktdiaoh4s7pgujcm5n9dihen.apps.googleusercontent.com",
              "client_type": 3
            }
          ]
        }
      }
    }
  ],
  "configuration_version": "1"
}